projectkit/__init__.py
projectkit/cli.py
projectkit/model/__init__.py
projectkit/model/project.py
projectkit/model/settings.py
projectkit/utils/__init__.py
projectkit/utils/map.py
projectkit/utils/pydantic.py
projectkit/utils/schema.py
projectkit/utils/typing.py
projectkit-0.2.1.dist-info/METADATA
projectkit-0.2.1.dist-info/WHEEL
projectkit-0.2.1.dist-info/RECORD
